tafnn_homedir/__init__.py
TAFNN-1.8.dist-info/LICENSE
TAFNN-1.8.dist-info/METADATA
TAFNN-1.8.dist-info/WHEEL
TAFNN-1.8.dist-info/top_level.txt
TAFNN-1.8.dist-info/RECORD
