Metadata-Version: 2.1
Name: TAFNN
Version: 1.8
Summary: Agent for Neural Network training supervision
Home-page: https://github.com/systemcorp-ai/TAFNN/archive/1.8.tar.gz
Author: SYSTEM CORP.
Author-email: contact@systemcorp.ai
License: UNKNOWN
Platform: UNKNOWN
Classifier: Programming Language :: Python :: 3.7
Classifier: License :: OSI Approved :: BSD License
Classifier: Operating System :: OS Independent
Classifier: Development Status :: 4 - Beta
